logilab_database-2.0-py3.12-nspkg.pth
logilab/database/__init__.py
logilab/database/fti.py
logilab/database/ftiparser.g
logilab/database/ftiparser.py
logilab/database/ftiquery.py
logilab/database/postgres.py
logilab/database/sqlgen.py
logilab/database/sqlite.py
logilab_database-2.0.dist-info/COPYING
logilab_database-2.0.dist-info/COPYING.LESSER
logilab_database-2.0.dist-info/METADATA
logilab_database-2.0.dist-info/WHEEL
logilab_database-2.0.dist-info/namespace_packages.txt
logilab_database-2.0.dist-info/top_level.txt
logilab_database-2.0.dist-info/RECORD
