Metadata-Version: 2.1
Name: logilab-database
Version: 2.0
Summary: true unified database access
Home-page: http://www.logilab.org/project/logilab-database
Author: Logilab
Author-email: contact@logilab.fr
License: LGPL
Classifier: Topic :: Database
Classifier: Programming Language :: Python
Classifier: Programming Language :: Python :: 3
Classifier: Programming Language :: Python :: 3 :: Only
Requires-Python: >=3
License-File: COPYING
License-File: COPYING.LESSER
Requires-Dist: setuptools
Requires-Dist: logilab-common <3.0.0,>=2.0.0
Requires-Dist: Yapps2-logilab
Requires-Dist: python-dateutil
